kobuddy/__init__.py
kobuddy/__main__.py
kobuddy/backup.py
kobuddy/common.py
kobuddy/kobo_device.py
kobuddy/py.typed
kobuddy/sqlite.py
kobuddy/tests/test_kobo.py
kobuddy/tests/test_rows.py
kobuddy-0.4.20241020.dist-info/LICENSE.txt
kobuddy-0.4.20241020.dist-info/METADATA
kobuddy-0.4.20241020.dist-info/WHEEL
kobuddy-0.4.20241020.dist-info/entry_points.txt
kobuddy-0.4.20241020.dist-info/top_level.txt
kobuddy-0.4.20241020.dist-info/RECORD
