Metadata-Version: 2.1
Name: kobuddy
Version: 0.4.20241020
Summary: Backup and extract data from your Kobo reader
Author-email: "Dima Gerasimov (@karlicoss)" <karlicoss@gmail.com>
Maintainer-email: "Dima Gerasimov (@karlicoss)" <karlicoss@gmail.com>
License: The MIT License (MIT)
Project-URL: Homepage, https://github.com/karlicoss/kobuddy
Requires-Python: >=3.9
License-File: LICENSE.txt
Provides-Extra: testing
Requires-Dist: pytest ; extra == 'testing'
Requires-Dist: ruff ; extra == 'testing'
Requires-Dist: mypy ; extra == 'testing'
Requires-Dist: lxml ; extra == 'testing'
